sofa/__init__.py
sofa/__main__.py
sofa/sofa_analyze.py
sofa/sofa_config.py
sofa/sofa_preprocess.py
sofa/sofa_print.py
sofa/sofa_record.py
sofa/sofa_viz.py
sofa/sofarun.py
sofalite-0.6.3.data/data/sofaboard/index.html
sofalite-0.6.3.dist-info/DESCRIPTION.rst
sofalite-0.6.3.dist-info/LICENSE.txt
sofalite-0.6.3.dist-info/METADATA
sofalite-0.6.3.dist-info/RECORD
sofalite-0.6.3.dist-info/WHEEL
sofalite-0.6.3.dist-info/entry_points.txt
sofalite-0.6.3.dist-info/metadata.json
sofalite-0.6.3.dist-info/top_level.txt
