Metadata-Version: 2.0
Name: sofalite
Version: 0.6.3
Summary: Swarm of Functions Analysis Tools
Home-page: https://github.com/cyliustack/sofa
Author: Cheng-Yueh Liu
Author-email: cyliustack@gmail.com
License: UNKNOWN
Keywords: sofa tracing performance
Platform: UNKNOWN
Classifier: Development Status :: 3 - Alpha
Classifier: Intended Audience :: Developers
Classifier: Topic :: Software Development :: Build Tools
Classifier: License :: OSI Approved :: Apache Software License
Classifier: Programming Language :: Python :: 3
Classifier: Programming Language :: Python :: 3.4
Requires-Dist: cxxfilt
Requires-Dist: networkx
Requires-Dist: numpy
